{"id":"0fma76ZZSVQ0ZDz8A-eFs","title":"Human Systems Life Action Redesign","vault":{"fsPath":"vault"},"type":"note","desc":"","links":[{"type":"wiki","from":{"fname":"session.human-systems-life-action-redesign","id":"0fma76ZZSVQ0ZDz8A-eFs","vaultName":"vault"},"value":"person.lorraine-selke","alias":"person.lorraine-selke","position":{"start":{"line":21,"column":3,"offset":767},"end":{"line":21,"column":28,"offset":792},"indent":[]},"xvault":false,"sameFile":false,"to":{"fname":"person.lorraine-selke"}},{"type":"wiki","from":{"fname":"session.human-systems-life-action-redesign","id":"0fma76ZZSVQ0ZDz8A-eFs","vaultName":"vault"},"value":"person.sara-ness","alias":"person.sara-ness","position":{"start":{"line":22,"column":3,"offset":795},"end":{"line":22,"column":23,"offset":815},"indent":[]},"xvault":false,"sameFile":false,"to":{"fname":"person.sara-ness"}},{"type":"wiki","from":{"fname":"session.human-systems-life-action-redesign","id":"0fma76ZZSVQ0ZDz8A-eFs","vaultName":"vault"},"value":"tags.topics.human-systems","alias":"#topics.human-systems","position":{"start":{"line":30,"column":3,"offset":841},"end":{"line":30,"column":24,"offset":862},"indent":[]},"xvault":false,"to":{"fname":"tags.topics.human-systems"}},{"type":"wiki","from":{"fname":"session.human-systems-life-action-redesign","id":"0fma76ZZSVQ0ZDz8A-eFs","vaultName":"vault"},"value":"tags.topics.life-action","alias":"#topics.life-action","position":{"start":{"line":31,"column":3,"offset":865},"end":{"line":31,"column":22,"offset":884},"indent":[]},"xvault":false,"to":{"fname":"tags.topics.life-action"}},{"from":{"fname":"the-stoa","vaultName":"vault"},"type":"backlink","position":{"start":{"line":501,"column":21,"offset":34959},"end":{"line":501,"column":67,"offset":35005},"indent":[]},"value":"session.human-systems-life-action-redesign"}],"anchors":{"persons":{"type":"header","text":"Persons","value":"persons","line":25,"column":0,"depth":2},"tags":{"type":"header","text":"Tags","value":"tags","line":30,"column":0,"depth":2},"topics":{"type":"header","text":"Topics","value":"topics","line":34,"column":0,"depth":2},"series":{"type":"header","text":"Series","value":"series","line":39,"column":0,"depth":2}},"fname":"session.human-systems-life-action-redesign","updated":1644961726951,"created":1588197600000,"parent":"rCGAoGPTc0QGctQnvunCs","children":[],"data":{},"contentHash":"bd0c542b5528910722837d6f7346b584","custom":{}}
