{"id":"11BXLa3KgMeej6M3GYdZp","title":"Rapture","vault":{"fsPath":"vault"},"type":"note","desc":"","links":[{"from":{"fname":"session.recapture-the-rapture","vaultName":"vault"},"type":"backlink","position":{"start":{"line":27,"column":3,"offset":1083},"end":{"line":27,"column":11,"offset":1091},"indent":[]},"value":"tags.rapture"}],"anchors":{},"fname":"tags.rapture","updated":1644961726962,"created":1644961726962,"parent":"iUO8dQ71CZW6WULc5pBh4","children":[],"data":{},"contentHash":"b9c3a195d2463d14512cc0cf89d9a724","custom":{}}
