{"id":"3GesI0uXeWSyhW1GMVa3b","title":"Afterlife","vault":{"fsPath":"vault"},"type":"note","desc":"","links":[{"from":{"fname":"session.afterlife-is-there-consciousness-after-death","vaultName":"vault"},"type":"backlink","position":{"start":{"line":25,"column":3,"offset":1400},"end":{"line":25,"column":13,"offset":1410},"indent":[]},"value":"tags.afterlife"}],"anchors":{},"fname":"tags.afterlife","updated":1644961726972,"created":1644961726972,"parent":"iUO8dQ71CZW6WULc5pBh4","children":[],"data":{},"contentHash":"ac80eab804fbfe843704ec87ad50e6bd","custom":{}}
