{"id":"6kHtg_j6Y0FyR0YmRpWLy","title":"Relevance","vault":{"fsPath":"vault"},"type":"note","desc":"","links":[{"from":{"fname":"session.part-moon-part-traveling-salesman-on-the-enduring-relevance-of-ivan-illich","vaultName":"vault"},"type":"backlink","position":{"start":{"line":29,"column":3,"offset":882},"end":{"line":29,"column":13,"offset":892},"indent":[]},"value":"tags.relevance"}],"anchors":{},"fname":"tags.relevance","updated":1644961726966,"created":1644961726966,"parent":"iUO8dQ71CZW6WULc5pBh4","children":[],"data":{},"contentHash":"858a9359842af24e99c73b4ba99fac7e","custom":{}}
