{"id":"6ZClYvy08f3UlHl6mhjC1","title":"Shadowplay","vault":{"fsPath":"vault"},"type":"note","desc":" Motherhood and Shadow","links":[{"type":"wiki","from":{"fname":"session.shadowplay-motherhood-and-shadow","id":"6ZClYvy08f3UlHl6mhjC1","vaultName":"vault"},"value":"person.lisa-marchiano","alias":"person.lisa-marchiano","position":{"start":{"line":26,"column":3,"offset":1106},"end":{"line":26,"column":28,"offset":1131},"indent":[]},"xvault":false,"sameFile":false,"to":{"fname":"person.lisa-marchiano"}},{"type":"wiki","from":{"fname":"session.shadowplay-motherhood-and-shadow","id":"6ZClYvy08f3UlHl6mhjC1","vaultName":"vault"},"value":"tags.shadowplay","alias":"#shadowplay","position":{"start":{"line":30,"column":3,"offset":1144},"end":{"line":30,"column":14,"offset":1155},"indent":[]},"xvault":false,"to":{"fname":"tags.shadowplay"}},{"type":"wiki","from":{"fname":"session.shadowplay-motherhood-and-shadow","id":"6ZClYvy08f3UlHl6mhjC1","vaultName":"vault"},"value":"tags.motherhood","alias":"#motherhood","position":{"start":{"line":31,"column":3,"offset":1158},"end":{"line":31,"column":14,"offset":1169},"indent":[]},"xvault":false,"to":{"fname":"tags.motherhood"}},{"type":"wiki","from":{"fname":"session.shadowplay-motherhood-and-shadow","id":"6ZClYvy08f3UlHl6mhjC1","vaultName":"vault"},"value":"tags.shadow","alias":"#shadow","position":{"start":{"line":32,"column":3,"offset":1172},"end":{"line":32,"column":10,"offset":1179},"indent":[]},"xvault":false,"to":{"fname":"tags.shadow"}},{"type":"wiki","from":{"fname":"session.shadowplay-motherhood-and-shadow","id":"6ZClYvy08f3UlHl6mhjC1","vaultName":"vault"},"value":"series.shadowplay","alias":"series.shadowplay","position":{"start":{"line":40,"column":3,"offset":1207},"end":{"line":40,"column":24,"offset":1228},"indent":[]},"xvault":false,"sameFile":false,"to":{"fname":"series.shadowplay"}},{"from":{"fname":"the-stoa","vaultName":"vault"},"type":"backlink","position":{"start":{"line":185,"column":21,"offset":13380},"end":{"line":185,"column":65,"offset":13424},"indent":[]},"value":"session.shadowplay-motherhood-and-shadow"},{"from":{"fname":"series.shadowplay","vaultName":"vault"},"type":"backlink","position":{"start":{"line":5,"column":3,"offset":309},"end":{"line":5,"column":82,"offset":388},"indent":[]},"value":"session.shadowplay-motherhood-and-shadow"}],"anchors":{"persons":{"type":"header","text":"Persons","value":"persons","line":30,"column":0,"depth":2},"tags":{"type":"header","text":"Tags","value":"tags","line":34,"column":0,"depth":2},"topics":{"type":"header","text":"Topics","value":"topics","line":40,"column":0,"depth":2},"series":{"type":"header","text":"Series","value":"series","line":44,"column":0,"depth":2}},"fname":"session.shadowplay-motherhood-and-shadow","updated":1644961726945,"created":1614726000000,"parent":"rCGAoGPTc0QGctQnvunCs","children":[],"data":{},"contentHash":"23b9ddc2627cf8e1c3eb25d0ab296f7c","custom":{}}
