{"id":"9CeNz9a0Ei3bVBsQw-tjT","title":"Anti-Social Virtue, or Cynical Enlightenment","vault":{"fsPath":"vault"},"type":"note","desc":"","links":[{"type":"wiki","from":{"fname":"session.anti-social-virtue-or-cynical-enlightenment","id":"9CeNz9a0Ei3bVBsQw-tjT","vaultName":"vault"},"value":"person.justin-murphy","alias":"person.justin-murphy","position":{"start":{"line":21,"column":3,"offset":998},"end":{"line":21,"column":27,"offset":1022},"indent":[]},"xvault":false,"sameFile":false,"to":{"fname":"person.justin-murphy"}},{"type":"wiki","from":{"fname":"session.anti-social-virtue-or-cynical-enlightenment","id":"9CeNz9a0Ei3bVBsQw-tjT","vaultName":"vault"},"value":"tags.topics.anti-social-virtue","alias":"#topics.anti-social-virtue","position":{"start":{"line":29,"column":3,"offset":1048},"end":{"line":29,"column":29,"offset":1074},"indent":[]},"xvault":false,"to":{"fname":"tags.topics.anti-social-virtue"}},{"type":"wiki","from":{"fname":"session.anti-social-virtue-or-cynical-enlightenment","id":"9CeNz9a0Ei3bVBsQw-tjT","vaultName":"vault"},"value":"tags.topics.cynical-enlightenment","alias":"#topics.cynical-enlightenment","position":{"start":{"line":30,"column":3,"offset":1077},"end":{"line":30,"column":32,"offset":1106},"indent":[]},"xvault":false,"to":{"fname":"tags.topics.cynical-enlightenment"}},{"from":{"fname":"the-stoa","vaultName":"vault"},"type":"backlink","position":{"start":{"line":481,"column":21,"offset":33590},"end":{"line":481,"column":76,"offset":33645},"indent":[]},"value":"session.anti-social-virtue-or-cynical-enlightenment"}],"anchors":{"persons":{"type":"header","text":"Persons","value":"persons","line":25,"column":0,"depth":2},"tags":{"type":"header","text":"Tags","value":"tags","line":29,"column":0,"depth":2},"topics":{"type":"header","text":"Topics","value":"topics","line":33,"column":0,"depth":2},"series":{"type":"header","text":"Series","value":"series","line":38,"column":0,"depth":2}},"fname":"session.anti-social-virtue-or-cynical-enlightenment","updated":1644961726950,"created":1589407200000,"parent":"rCGAoGPTc0QGctQnvunCs","children":[],"data":{},"contentHash":"6d9def9308db12a29d64fee7365f3281","custom":{}}
