{"id":"AjswPSyereWLECksBbQek","title":"Evolving Ground","vault":{"fsPath":"vault"},"type":"note","desc":" 04 Principle & Function","links":[{"type":"wiki","from":{"fname":"session.evolving-ground-04-principle-and-function","id":"AjswPSyereWLECksBbQek","vaultName":"vault"},"value":"person.charlie-awbery","alias":"person.charlie-awbery","position":{"start":{"line":22,"column":3,"offset":1114},"end":{"line":22,"column":28,"offset":1139},"indent":[]},"xvault":false,"sameFile":false,"to":{"fname":"person.charlie-awbery"}},{"type":"wiki","from":{"fname":"session.evolving-ground-04-principle-and-function","id":"AjswPSyereWLECksBbQek","vaultName":"vault"},"value":"person.jared-janes","alias":"person.jared-janes","position":{"start":{"line":23,"column":3,"offset":1142},"end":{"line":23,"column":25,"offset":1164},"indent":[]},"xvault":false,"sameFile":false,"to":{"fname":"person.jared-janes"}},{"type":"wiki","from":{"fname":"session.evolving-ground-04-principle-and-function","id":"AjswPSyereWLECksBbQek","vaultName":"vault"},"value":"tags.ground","alias":"#ground","position":{"start":{"line":27,"column":3,"offset":1177},"end":{"line":27,"column":10,"offset":1184},"indent":[]},"xvault":false,"to":{"fname":"tags.ground"}},{"type":"wiki","from":{"fname":"session.evolving-ground-04-principle-and-function","id":"AjswPSyereWLECksBbQek","vaultName":"vault"},"value":"tags.principle","alias":"#principle","position":{"start":{"line":28,"column":3,"offset":1187},"end":{"line":28,"column":13,"offset":1197},"indent":[]},"xvault":false,"to":{"fname":"tags.principle"}},{"type":"wiki","from":{"fname":"session.evolving-ground-04-principle-and-function","id":"AjswPSyereWLECksBbQek","vaultName":"vault"},"value":"tags.function","alias":"#function","position":{"start":{"line":29,"column":3,"offset":1200},"end":{"line":29,"column":12,"offset":1209},"indent":[]},"xvault":false,"to":{"fname":"tags.function"}},{"type":"wiki","from":{"fname":"session.evolving-ground-04-principle-and-function","id":"AjswPSyereWLECksBbQek","vaultName":"vault"},"value":"series.evolving-ground","alias":"series.evolving-ground","position":{"start":{"line":37,"column":3,"offset":1237},"end":{"line":37,"column":29,"offset":1263},"indent":[]},"xvault":false,"sameFile":false,"to":{"fname":"series.evolving-ground"}},{"from":{"fname":"the-stoa","vaultName":"vault"},"type":"backlink","position":{"start":{"line":135,"column":21,"offset":9649},"end":{"line":135,"column":74,"offset":9702},"indent":[]},"value":"session.evolving-ground-04-principle-and-function"},{"from":{"fname":"series.evolving-ground","vaultName":"vault"},"type":"backlink","position":{"start":{"line":3,"column":3,"offset":67},"end":{"line":3,"column":98,"offset":162},"indent":[]},"value":"session.evolving-ground-04-principle-and-function"}],"anchors":{"persons":{"type":"header","text":"Persons","value":"persons","line":26,"column":0,"depth":2},"tags":{"type":"header","text":"Tags","value":"tags","line":31,"column":0,"depth":2},"topics":{"type":"header","text":"Topics","value":"topics","line":37,"column":0,"depth":2},"series":{"type":"header","text":"Series","value":"series","line":41,"column":0,"depth":2}},"fname":"session.evolving-ground-04-principle-and-function","updated":1644961726947,"created":1621720800000,"parent":"rCGAoGPTc0QGctQnvunCs","children":[],"data":{},"contentHash":"c3555070b926ac6c909c146bc691360e","custom":{}}
