{"id":"hzrq1U08K0CeqWHclSnM8","title":"Hunters","vault":{"fsPath":"vault"},"type":"note","desc":"","links":[{"from":{"fname":"session.hunters-of-souls-eros-unchained-dialogos","vaultName":"vault"},"type":"backlink","position":{"start":{"line":30,"column":3,"offset":1069},"end":{"line":30,"column":11,"offset":1077},"indent":[]},"value":"tags.hunters"}],"anchors":{},"fname":"tags.hunters","updated":1644961726962,"created":1644961726962,"parent":"iUO8dQ71CZW6WULc5pBh4","children":[],"data":{},"contentHash":"d7e02b9f3b46b94b16b72e4af9b7fe4a","custom":{}}
