{"id":"k0tN8vu_IpBHKM2SezSkm","title":"Situational Assessment","vault":{"fsPath":"vault"},"type":"note","desc":"","links":[{"type":"wiki","from":{"fname":"session.situational-assessment-2","id":"k0tN8vu_IpBHKM2SezSkm","vaultName":"vault"},"value":"person.jordan-hall","alias":"person.jordan-hall","position":{"start":{"line":19,"column":3,"offset":617},"end":{"line":19,"column":25,"offset":639},"indent":[]},"xvault":false,"sameFile":false,"to":{"fname":"person.jordan-hall"}},{"type":"wiki","from":{"fname":"session.situational-assessment-2","id":"k0tN8vu_IpBHKM2SezSkm","vaultName":"vault"},"value":"tags.topics.situational-assessment","alias":"#topics.situational-assessment","position":{"start":{"line":27,"column":3,"offset":665},"end":{"line":27,"column":33,"offset":695},"indent":[]},"xvault":false,"to":{"fname":"tags.topics.situational-assessment"}},{"type":"wiki","from":{"fname":"session.situational-assessment-2","id":"k0tN8vu_IpBHKM2SezSkm","vaultName":"vault"},"value":"series.situational-assessment","alias":"series.situational-assessment","position":{"start":{"line":31,"column":3,"offset":710},"end":{"line":31,"column":36,"offset":743},"indent":[]},"xvault":false,"sameFile":false,"to":{"fname":"series.situational-assessment"}},{"from":{"fname":"the-stoa","vaultName":"vault"},"type":"backlink","position":{"start":{"line":522,"column":21,"offset":36389},"end":{"line":522,"column":57,"offset":36425},"indent":[]},"value":"session.situational-assessment-2"},{"from":{"fname":"series.situational-assessment","vaultName":"vault"},"type":"backlink","position":{"start":{"line":6,"column":3,"offset":308},"end":{"line":6,"column":73,"offset":378},"indent":[]},"value":"session.situational-assessment-2"}],"anchors":{"persons":{"type":"header","text":"Persons","value":"persons","line":23,"column":0,"depth":2},"tags":{"type":"header","text":"Tags","value":"tags","line":27,"column":0,"depth":2},"topics":{"type":"header","text":"Topics","value":"topics","line":31,"column":0,"depth":2},"series":{"type":"header","text":"Series","value":"series","line":35,"column":0,"depth":2}},"fname":"session.situational-assessment-2","updated":1644961726947,"created":1586022911000,"parent":"rCGAoGPTc0QGctQnvunCs","children":[],"data":{},"contentHash":"c9e26553fa71d1668c007ee9d20bc817","custom":{}}
