{"id":"LLd1Ncsdaff_8dtTCYjib","title":"Strange Times","vault":{"fsPath":"vault"},"type":"note","desc":" A Contemplative Perspective","links":[{"type":"wiki","from":{"fname":"session.strange-times-a-contemplative-perspective","id":"LLd1Ncsdaff_8dtTCYjib","vaultName":"vault"},"value":"person.shinzen-young","alias":"person.shinzen-young","position":{"start":{"line":21,"column":3,"offset":686},"end":{"line":21,"column":27,"offset":710},"indent":[]},"xvault":false,"sameFile":false,"to":{"fname":"person.shinzen-young"}},{"type":"wiki","from":{"fname":"session.strange-times-a-contemplative-perspective","id":"LLd1Ncsdaff_8dtTCYjib","vaultName":"vault"},"value":"tags.topics.strange-times","alias":"#topics.strange-times","position":{"start":{"line":29,"column":3,"offset":736},"end":{"line":29,"column":24,"offset":757},"indent":[]},"xvault":false,"to":{"fname":"tags.topics.strange-times"}},{"type":"wiki","from":{"fname":"session.strange-times-a-contemplative-perspective","id":"LLd1Ncsdaff_8dtTCYjib","vaultName":"vault"},"value":"tags.topics.contemplative-perspective","alias":"#topics.contemplative-perspective","position":{"start":{"line":30,"column":3,"offset":760},"end":{"line":30,"column":36,"offset":793},"indent":[]},"xvault":false,"to":{"fname":"tags.topics.contemplative-perspective"}},{"from":{"fname":"the-stoa","vaultName":"vault"},"type":"backlink","position":{"start":{"line":267,"column":21,"offset":19344},"end":{"line":267,"column":74,"offset":19397},"indent":[]},"value":"session.strange-times-a-contemplative-perspective"}],"anchors":{"persons":{"type":"header","text":"Persons","value":"persons","line":25,"column":0,"depth":2},"tags":{"type":"header","text":"Tags","value":"tags","line":29,"column":0,"depth":2},"topics":{"type":"header","text":"Topics","value":"topics","line":33,"column":0,"depth":2},"series":{"type":"header","text":"Series","value":"series","line":38,"column":0,"depth":2}},"fname":"session.strange-times-a-contemplative-perspective","updated":1644961726946,"created":1606172400000,"parent":"rCGAoGPTc0QGctQnvunCs","children":[],"data":{},"contentHash":"45935176d967b6a62eeef28717c91a84","custom":{}}
