{"id":"OQELatEKp7xgmLTzLd2d5","title":"Live Players","vault":{"fsPath":"vault"},"type":"note","desc":"","links":[{"type":"wiki","from":{"fname":"session.live-players-2","id":"OQELatEKp7xgmLTzLd2d5","vaultName":"vault"},"value":"person.samo-burja","alias":"person.samo-burja","position":{"start":{"line":19,"column":3,"offset":870},"end":{"line":19,"column":24,"offset":891},"indent":[]},"xvault":false,"sameFile":false,"to":{"fname":"person.samo-burja"}},{"type":"wiki","from":{"fname":"session.live-players-2","id":"OQELatEKp7xgmLTzLd2d5","vaultName":"vault"},"value":"tags.players","alias":"#players","position":{"start":{"line":23,"column":3,"offset":904},"end":{"line":23,"column":11,"offset":912},"indent":[]},"xvault":false,"to":{"fname":"tags.players"}},{"type":"wiki","from":{"fname":"session.live-players-2","id":"OQELatEKp7xgmLTzLd2d5","vaultName":"vault"},"value":"series.live-players","alias":"series.live-players","position":{"start":{"line":31,"column":3,"offset":940},"end":{"line":31,"column":26,"offset":963},"indent":[]},"xvault":false,"sameFile":false,"to":{"fname":"series.live-players"}},{"from":{"fname":"the-stoa","vaultName":"vault"},"type":"backlink","position":{"start":{"line":429,"column":21,"offset":30119},"end":{"line":429,"column":47,"offset":30145},"indent":[]},"value":"session.live-players-2"},{"from":{"fname":"series.live-players","vaultName":"vault"},"type":"backlink","position":{"start":{"line":4,"column":3,"offset":107},"end":{"line":4,"column":53,"offset":157},"indent":[]},"value":"session.live-players-2"}],"anchors":{"persons":{"type":"header","text":"Persons","value":"persons","line":23,"column":0,"depth":2},"tags":{"type":"header","text":"Tags","value":"tags","line":27,"column":0,"depth":2},"topics":{"type":"header","text":"Topics","value":"topics","line":31,"column":0,"depth":2},"series":{"type":"header","text":"Series","value":"series","line":35,"column":0,"depth":2}},"fname":"session.live-players-2","updated":1644961726950,"created":1592606474000,"parent":"rCGAoGPTc0QGctQnvunCs","children":[],"data":{},"contentHash":"de3c169d7dc36e0b57bf3687a6142ef9","custom":{}}
