{"id":"PdYtFJEkKuR2f0MWtLFNr","title":"View","vault":{"fsPath":"vault"},"type":"note","desc":"","links":[{"from":{"fname":"session.collective-intelligence-a-view-from-the-existential-trenches","vaultName":"vault"},"type":"backlink","position":{"start":{"line":35,"column":3,"offset":1611},"end":{"line":35,"column":8,"offset":1616},"indent":[]},"value":"tags.view"},{"from":{"fname":"session.evolving-ground-02-view","vaultName":"vault"},"type":"backlink","position":{"start":{"line":27,"column":3,"offset":1021},"end":{"line":27,"column":8,"offset":1026},"indent":[]},"value":"tags.view"},{"from":{"fname":"session.john-vervaeke-the-view-from-above-a-transformation-of-perspectival-and-participatory-knowing","vaultName":"vault"},"type":"backlink","position":{"start":{"line":27,"column":3,"offset":1765},"end":{"line":27,"column":8,"offset":1770},"indent":[]},"value":"tags.view"},{"from":{"fname":"session.the-view-from-above","vaultName":"vault"},"type":"backlink","position":{"start":{"line":21,"column":3,"offset":522},"end":{"line":21,"column":8,"offset":527},"indent":[]},"value":"tags.view"}],"anchors":{},"fname":"tags.view","updated":1644961726956,"created":1644961726956,"parent":"iUO8dQ71CZW6WULc5pBh4","children":[],"data":{},"contentHash":"375f34354c1fdb4068e10c120a75fc17","custom":{}}
