{"id":"pEtOgZ0XfsW4vkcXvguGf","title":"Dialogue","vault":{"fsPath":"vault"},"type":"note","desc":"","links":[{"from":{"fname":"session.reflective-structured-dialogue","vaultName":"vault"},"type":"backlink","position":{"start":{"line":27,"column":3,"offset":824},"end":{"line":27,"column":12,"offset":833},"indent":[]},"value":"tags.dialogue"}],"anchors":{},"fname":"tags.dialogue","updated":1644961726970,"created":1644961726970,"parent":"iUO8dQ71CZW6WULc5pBh4","children":[],"data":{},"contentHash":"a34ebd8c02644d7b5ba296afdbf55522","custom":{}}
