{"id":"RW0PsGb8CIgkUo_MOhV5E","title":"The Bridge","vault":{"fsPath":"vault"},"type":"note","desc":"","links":[{"type":"wiki","from":{"fname":"series.the-bridge","id":"RW0PsGb8CIgkUo_MOhV5E","vaultName":"vault"},"value":"session.the-bridge-deep-dives-s1-neurophilosophy","alias":"The Bridge:  Deep-Dives. S1. Neurophilosophy","position":{"start":{"line":2,"column":3,"offset":3},"end":{"line":2,"column":100,"offset":100},"indent":[]},"xvault":false,"sameFile":false,"to":{"fname":"session.the-bridge-deep-dives-s1-neurophilosophy"}},{"type":"wiki","from":{"fname":"series.the-bridge","id":"RW0PsGb8CIgkUo_MOhV5E","vaultName":"vault"},"value":"session.the-bridge-deep-dives-s3-bridge-and-communitas","alias":"The Bridge:  Deep-Dives. S3. Bridge and Communitas","position":{"start":{"line":3,"column":3,"offset":103},"end":{"line":3,"column":112,"offset":212},"indent":[]},"xvault":false,"sameFile":false,"to":{"fname":"session.the-bridge-deep-dives-s3-bridge-and-communitas"}},{"type":"wiki","from":{"fname":"series.the-bridge","id":"RW0PsGb8CIgkUo_MOhV5E","vaultName":"vault"},"value":"session.the-bridge-deep-dives-s2-embodied-practice","alias":"The Bridge:  Deep-Dives. S2. Embodied Practice","position":{"start":{"line":4,"column":3,"offset":215},"end":{"line":4,"column":104,"offset":316},"indent":[]},"xvault":false,"sameFile":false,"to":{"fname":"session.the-bridge-deep-dives-s2-embodied-practice"}},{"type":"wiki","from":{"fname":"series.the-bridge","id":"RW0PsGb8CIgkUo_MOhV5E","vaultName":"vault"},"value":"session.the-bridge-rationality-to-\"woo\"","alias":"The Bridge:  Rationality to \"Woo\"","position":{"start":{"line":5,"column":3,"offset":319},"end":{"line":5,"column":80,"offset":396},"indent":[]},"xvault":false,"sameFile":false,"to":{"fname":"session.the-bridge-rationality-to-\"woo\""}},{"type":"wiki","from":{"fname":"series.the-bridge","id":"RW0PsGb8CIgkUo_MOhV5E","vaultName":"vault"},"value":"session.the-bridge-deep-dives-s4-bridging-science-and-magic","alias":"The Bridge:  Deep-Dives. S4. Bridging Science and Magic","position":{"start":{"line":6,"column":3,"offset":399},"end":{"line":6,"column":122,"offset":518},"indent":[]},"xvault":false,"sameFile":false,"to":{"fname":"session.the-bridge-deep-dives-s4-bridging-science-and-magic"}},{"from":{"fname":"session.the-bridge-deep-dives-s1-neurophilosophy","vaultName":"vault"},"type":"backlink","position":{"start":{"line":45,"column":3,"offset":1185},"end":{"line":45,"column":24,"offset":1206},"indent":[]},"value":"series.the-bridge"},{"from":{"fname":"session.the-bridge-deep-dives-s2-embodied-practice","vaultName":"vault"},"type":"backlink","position":{"start":{"line":45,"column":3,"offset":1175},"end":{"line":45,"column":24,"offset":1196},"indent":[]},"value":"series.the-bridge"},{"from":{"fname":"session.the-bridge-deep-dives-s3-bridge-and-communitas","vaultName":"vault"},"type":"backlink","position":{"start":{"line":46,"column":3,"offset":1344},"end":{"line":46,"column":24,"offset":1365},"indent":[]},"value":"series.the-bridge"},{"from":{"fname":"session.the-bridge-deep-dives-s4-bridging-science-and-magic","vaultName":"vault"},"type":"backlink","position":{"start":{"line":44,"column":3,"offset":1274},"end":{"line":44,"column":24,"offset":1295},"indent":[]},"value":"series.the-bridge"},{"from":{"fname":"session.the-bridge-rationality-to-\"woo\"","vaultName":"vault"},"type":"backlink","position":{"start":{"line":43,"column":3,"offset":1824},"end":{"line":43,"column":24,"offset":1845},"indent":[]},"value":"series.the-bridge"}],"anchors":{},"fname":"series.the-bridge","updated":1644961726973,"created":1644961726973,"parent":"fyc0e5X7VHGFlHAdPLusE","children":[],"data":{},"contentHash":"3944b02405b97581d37aa2ab6a58581c","custom":{}}
