{"id":"sHhqnykyqe7Ph4ykpoVEX","title":"Class","vault":{"fsPath":"vault"},"type":"note","desc":"","links":[{"from":{"fname":"session.homestead-incubator-a-class-for-resilience-and-community","vaultName":"vault"},"type":"backlink","position":{"start":{"line":27,"column":3,"offset":2264},"end":{"line":27,"column":9,"offset":2270},"indent":[]},"value":"tags.class"}],"anchors":{},"fname":"tags.class","updated":1644961726972,"created":1644961726972,"parent":"iUO8dQ71CZW6WULc5pBh4","children":[],"data":{},"contentHash":"fe3c10974e77a7f222685f45fdb08c22","custom":{}}
