{"id":"x0WN9YUjkJmkcPS3rPOmS","title":"On the Metapolitics of Pandemics","vault":{"fsPath":"vault"},"type":"note","desc":"","links":[{"type":"wiki","from":{"fname":"session.on-the-metapolitics-of-pandemics","id":"x0WN9YUjkJmkcPS3rPOmS","vaultName":"vault"},"value":"person.zachary-stein","alias":"person.zachary-stein","position":{"start":{"line":19,"column":3,"offset":642},"end":{"line":19,"column":27,"offset":666},"indent":[]},"xvault":false,"sameFile":false,"to":{"fname":"person.zachary-stein"}},{"type":"wiki","from":{"fname":"session.on-the-metapolitics-of-pandemics","id":"x0WN9YUjkJmkcPS3rPOmS","vaultName":"vault"},"value":"tags.metapolitics","alias":"#metapolitics","position":{"start":{"line":23,"column":3,"offset":679},"end":{"line":23,"column":16,"offset":692},"indent":[]},"xvault":false,"to":{"fname":"tags.metapolitics"}},{"type":"wiki","from":{"fname":"session.on-the-metapolitics-of-pandemics","id":"x0WN9YUjkJmkcPS3rPOmS","vaultName":"vault"},"value":"tags.pandemics","alias":"#pandemics","position":{"start":{"line":24,"column":3,"offset":695},"end":{"line":24,"column":13,"offset":705},"indent":[]},"xvault":false,"to":{"fname":"tags.pandemics"}},{"from":{"fname":"the-stoa","vaultName":"vault"},"type":"backlink","position":{"start":{"line":513,"column":21,"offset":35769},"end":{"line":513,"column":65,"offset":35813},"indent":[]},"value":"session.on-the-metapolitics-of-pandemics"}],"anchors":{"persons":{"type":"header","text":"Persons","value":"persons","line":23,"column":0,"depth":2},"tags":{"type":"header","text":"Tags","value":"tags","line":27,"column":0,"depth":2},"topics":{"type":"header","text":"Topics","value":"topics","line":32,"column":0,"depth":2},"series":{"type":"header","text":"Series","value":"series","line":36,"column":0,"depth":2}},"fname":"session.on-the-metapolitics-of-pandemics","updated":1644961726948,"created":1586922089000,"parent":"rCGAoGPTc0QGctQnvunCs","children":[],"data":{},"contentHash":"4886c6ef8689ae3f917b489d20a544df","custom":{}}
